Metadata-Version: 1.0
Name: umalqurra
Version: 0.1
Summary: Date Api that support Hijri Umalqurra calendar. Features: 1-Convert Gregorian to Hijri 2-Convert Hijri to Gregorian 3-give the arabic name of the hijri month 4-give the english name of the gregorian month 5-give the day name in Arabic and English 6-give the current day both in Hijri and Gregorian
Home-page: https://github.com/tytkal/python-hijiri-ummalqura
Author:  Khalid Al-hussayen
Author-email: tytkal@gmail.com
License: Waqef
Platform: UNKNOWN
